{
  "orders": [
    {
      "text": "Marin just purchased Elgato Prompter Camera Plates"
    },
    {
      "text": "Tristen just purchased Arctis Pro Wireless Secretlab MAGNUS Version"
    },
    {
      "text": "Andrew just purchased Arctis Pro Wireless NOVA and ELITE Secretlab MAGNUS Version"
    },
    {
      "text": "Jack just purchased Elgato Wave XLR Mount"
    },
    {
      "text": "Faisal just purchased Elgato Key Light Grid Cover"
    },
    {
      "text": "Makoto just purchased Stream Deck Mk.2 Wood Face Plate"
    },
    {
      "text": "Philip just purchased Elgato Prompter Camera Plates"
    },
    {
      "text": "patrick just purchased Elgato Key Light Grid Cover"
    },
    {
      "text": "Alex just purchased Elgato Wave XLR Mount"
    },
    {
      "text": "bree just purchased Skadis/Uppspel Controller Holder"
    }
  ]
}